json_log_viewer/__init__.py
json_log_viewer/__main__.py
json_log_viewer/extractor/__init__.py
json_log_viewer/extractor/extract.py
json_log_viewer/extractor/test_extract.py
json_log_viewer/logs/__init__.py
json_log_viewer/logs/log.py
json_log_viewer/logs/test_log.py
json_log_viewer/logs/tree.py
json_log_viewer/test_version.py
json_log_viewer-0.1.2.dist-info/METADATA
json_log_viewer-0.1.2.dist-info/WHEEL
json_log_viewer-0.1.2.dist-info/entry_points.txt
json_log_viewer-0.1.2.dist-info/RECORD
