Metadata-Version: 2.1
Name: json-log-viewer
Version: 0.1.2
Summary: 
Author: Samuel Broster
Author-email: sam@broster.dev
Requires-Python: >=3.11,<4.0
Classifier: Programming Language :: Python :: 3
Classifier: Programming Language :: Python :: 3.11
Requires-Dist: docopt (>=0.6.2,<0.7.0)
Requires-Dist: pydantic (>=1.10.7,<2.0.0)
Requires-Dist: textual (>=0.26.0,<0.27.0)
